mechanize/__init__.py
mechanize/_auth.py
mechanize/_clientcookie.py
mechanize/_debug.py
mechanize/_entities.py
mechanize/_equiv.py
mechanize/_form.py
mechanize/_form_controls.py
mechanize/_gzip.py
mechanize/_headersutil.py
mechanize/_html.py
mechanize/_http.py
mechanize/_mechanize.py
mechanize/_opener.py
mechanize/_request.py
mechanize/_response.py
mechanize/_rfc3986.py
mechanize/_sockettimeout.py
mechanize/_testcase.py
mechanize/_urllib2.py
mechanize/_urllib2_fork.py
mechanize/_useragent.py
mechanize/_util.py
mechanize/_version.py
mechanize/polyglot.py
mechanize-0.4.9.dist-info/LICENSE
mechanize-0.4.9.dist-info/METADATA
mechanize-0.4.9.dist-info/WHEEL
mechanize-0.4.9.dist-info/top_level.txt
mechanize-0.4.9.dist-info/zip-safe
mechanize-0.4.9.dist-info/RECORD
