Metadata-Version: 2.1
Name: mechanize
Version: 0.4.9
Summary: Stateful, programmatic web browsing
Home-page: https://github.com/python-mechanize/mechanize
Author: Kovid Goyal
Author-email: no@no.no
License: BSD
Platform: any
Classifier: Development Status :: 5 - Production/Stable
Classifier: Intended Audience :: Developers
Classifier: Intended Audience :: System Administrators
Classifier: License :: OSI Approved :: BSD License
Classifier: Natural Language :: English
Classifier: Operating System :: OS Independent
Classifier: Programming Language :: Python
Classifier: Topic :: Internet
Classifier: Topic :: Internet :: File Transfer Protocol (FTP)
Classifier: Topic :: Internet :: WWW/HTTP
Classifier: Topic :: Internet :: WWW/HTTP :: Browsers
Classifier: Topic :: Internet :: WWW/HTTP :: Indexing/Search
Classifier: Topic :: Internet :: WWW/HTTP :: Site Management
Classifier: Topic :: Internet :: WWW/HTTP :: Site Management :: Link Checking
Classifier: Topic :: Software Development :: Libraries
Classifier: Topic :: Software Development :: Libraries :: Python Modules
Classifier: Topic :: Software Development :: Testing
Classifier: Topic :: Software Development :: Testing :: Traffic Generation
Classifier: Topic :: System :: Archiving :: Mirroring
Classifier: Topic :: System :: Networking :: Monitoring
Classifier: Topic :: System :: Systems Administration
Classifier: Topic :: Text Processing
Classifier: Topic :: Text Processing :: Markup
Classifier: Topic :: Text Processing :: Markup :: HTML
Classifier: Topic :: Text Processing :: Markup :: XML
License-File: LICENSE
Requires-Dist: html5lib>=0.999999999
Provides-Extra: fast
Requires-Dist: html5-parser>=0.4.4; extra == "fast"
Provides-Extra: test
Requires-Dist: twisted; extra == "test"
Requires-Dist: service_identity; extra == "test"
Requires-Dist: six; extra == "test"
Requires-Dist: html5lib; extra == "test"
Provides-Extra: binarytest
Requires-Dist: lxml; extra == "binarytest"
Requires-Dist: html5-parser; extra == "binarytest"
